paaster_cli/__init__.py
paaster_cli/misc.py
paaster_cli/storage.py
paaster-1.2.6.dist-info/METADATA
paaster-1.2.6.dist-info/WHEEL
paaster-1.2.6.dist-info/entry_points.txt
paaster-1.2.6.dist-info/licenses/LICENSE
paaster-1.2.6.dist-info/RECORD
