Metadata-Version: 2.4
Name: paaster
Version: 1.2.6
Summary: Upload locally encrypted pastes from your terminal to Paaster
License: GPL-3.0
License-File: LICENSE
Author: WardPearce
Author-email: wardpearce@protonmail.com
Requires-Python: >=3.10,<4.0
Classifier: License :: OSI Approved :: GNU General Public License v3 (GPLv3)
Classifier: Programming Language :: Python :: 3
Classifier: Programming Language :: Python :: 3.10
Classifier: Programming Language :: Python :: 3.11
Classifier: Programming Language :: Python :: 3.12
Classifier: Programming Language :: Python :: 3.13
Classifier: Programming Language :: Python :: 3.14
Requires-Dist: click (>=8.1.3,<9.0.0)
Requires-Dist: pyperclip (>=1.8.2,<2.0.0)
Requires-Dist: pysodium (>=0.7.12,<0.8.0)
Requires-Dist: requests (>=2.28.2,<3.0.0)
